chlt/Chinese_learn.py
chlt/__init__.py
chlt/gif_play.py
chlt/playsound.py
chlt/source/bxe4xb8x89.mp3
chlt/source/bxe4xbax94.mp3
chlt/source/bxe5x8dx81.mp3
chlt/source/bxe5x91xa8.mp3
chlt/source/bxe5x95x86.mp3
chlt/source/bxe5x9bxbd.mp3
chlt/source/bxe5xa4x8f.mp3
chlt/source/bxe5xadx90.mp3
chlt/source/bxe6x98x8e.mp3
chlt/source/bxe6x99x8b.mp3
chlt/source/bxe6x9cx9d.mp3
chlt/source/bxe8x80x81.mp3
chlt/source/bxe8xa5xbf.mp3
chlt/source/周.gif
chlt/source/商.gif
chlt/source/夏.gif
chlt/source/夏.mp3
chlt/source/大.gif
chlt/source/大.mp3
chlt/source/朝.gif
chlt/source/玩.gif
chlt/source/玩.mp3
chlt/source/老.gif
chlt/source/西.gif
chlt-0.2.3.dist-info/METADATA
chlt-0.2.3.dist-info/WHEEL
chlt-0.2.3.dist-info/licenses/LICENSE
chlt-0.2.3.dist-info/RECORD
