Metadata-Version: 2.1
Name: chlt
Version: 0.2.3
Summary: It is a tool to learn how to read and write Chinese Characters.
Project-URL: Homepage, https://gitee.com/shawnyanwang/chinese-learning-tool
Project-URL: Bug Tracker, https://gitee.com/shawnyanwang/chinese-learning-tool/issues
Author-email: shawn yan wang <shawnyanwang@gmail.com>
Classifier: License :: OSI Approved :: MIT License
Classifier: Operating System :: OS Independent
Classifier: Programming Language :: Python :: 3
Requires-Python: >=3.7
Requires-Dist: bs4>=0.0.1
Requires-Dist: gtts>=2.2.4
Requires-Dist: pillow>=9.0.1
Requires-Dist: playsound>=1.2.2
Requires-Dist: pywin32>=302
Requires-Dist: requests>=2.27.1
Requires-Dist: tqdm>=4.63.0
Requires-Dist: urllib3>=1.26.8
